hypatia/__init__.py
hypatia/actor.py
hypatia/animatedsprite.py
hypatia/constants.py
hypatia/controllers.py
hypatia/dialog.py
hypatia/game.py
hypatia/physics.py
hypatia/player.py
hypatia/render.py
hypatia/resources.py
hypatia/sound.py
hypatia/sprites.py
hypatia/tiles.py
hypatia_engine-0.3.6.dist-info/DESCRIPTION.rst
hypatia_engine-0.3.6.dist-info/METADATA
hypatia_engine-0.3.6.dist-info/RECORD
hypatia_engine-0.3.6.dist-info/WHEEL
hypatia_engine-0.3.6.dist-info/metadata.json
hypatia_engine-0.3.6.dist-info/top_level.txt
