Metadata-Version: 2.0
Name: hypatia-engine
Version: 0.3.6
Summary: 2D action adventure game engine
Home-page: http://hypatia-engine.github.io/hypatia
Author: Lillian Lemmer
Author-email: lillian.lynn.lemmer@gmail.com
License: MIT
Download-URL: https://github.com/hypatia-engine/hypatia/releases/tag/0.3.6
Keywords: games gaming development sprites adventure game tilemap tilesheet zelda gamedev 2d
Platform: UNKNOWN
Classifier: Development Status :: 3 - Alpha
Classifier: Intended Audience :: Developers
Classifier: Natural Language :: English
Classifier: License :: OSI Approved :: MIT License
Classifier: Programming Language :: Python :: 2.7
Classifier: Programming Language :: Python :: 3.4
Classifier: Operating System :: Microsoft :: Windows :: Windows 7
Classifier: Operating System :: Microsoft :: Windows :: Windows Vista
Classifier: Operating System :: Microsoft :: Windows :: Windows XP
Classifier: Operating System :: Microsoft :: Windows
Classifier: Operating System :: POSIX :: BSD :: FreeBSD
Classifier: Operating System :: POSIX :: Linux
Classifier: Topic :: Games/Entertainment :: Role-Playing
Classifier: Topic :: Software Development :: Libraries :: pygame
Requires-Dist: Pillow (>=2)
Requires-Dist: enum34
